croudtech_ecs_tools/__init__.py
croudtech_ecs_tools/cli.py
croudtech_ecs_tools/ecs.py
croudtech_ecs_tools-0.1.8.dist-info/LICENSE
croudtech_ecs_tools-0.1.8.dist-info/METADATA
croudtech_ecs_tools-0.1.8.dist-info/WHEEL
croudtech_ecs_tools-0.1.8.dist-info/entry_points.txt
croudtech_ecs_tools-0.1.8.dist-info/top_level.txt
croudtech_ecs_tools-0.1.8.dist-info/RECORD
